linkedin_automator/__init__.py
linkedin_automator/extractor.py
linkedin_automator/linkedin_automator.py
linkedin_automator-0.3.0.dist-info/METADATA
linkedin_automator-0.3.0.dist-info/WHEEL
linkedin_automator-0.3.0.dist-info/top_level.txt
linkedin_automator-0.3.0.dist-info/RECORD
