Metadata-Version: 2.1
Name: linkedin-automator
Version: 0.3.0
Summary: A Python library to automate various operations on LinkedIn posts, comments, and replies.
Home-page: https://github.com/PalestinianVoices/linkedin_automator
Author: Hala H. & Essam W.
License: MIT
Classifier: Intended Audience :: Developers
Classifier: License :: OSI Approved :: MIT License
Classifier: Programming Language :: Python
Classifier: Programming Language :: Python :: 3
Classifier: Programming Language :: Python :: 3.6
Classifier: Programming Language :: Python :: 3.7
Classifier: Programming Language :: Python :: 3.8
Classifier: Programming Language :: Python :: 3.9
Classifier: Operating System :: OS Independent
Requires-Dist: linkedin-api (==2.3.0)
Requires-Dist: python-dotenv (==1.0.1)
Requires-Dist: Requests (==2.32.3)
Requires-Dist: tqdm (==4.66.2)
